Metadata-Version: 1.0
Name: flask-gae-blobstore
Version: 1.0.2
Summary: Flask extension module for working with the blobstore & files apis on App Engine.
Home-page: http://github.com/gregorynicholas/flask-gae_blobstore
Author: gregorynicholas
Author-email: UNKNOWN
License: MIT
Platform: any
Classifier: Development Status :: 4 - Beta
Classifier: Environment :: Web Environment
Classifier: Intended Audience :: Developers
Classifier: License :: OSI Approved :: MIT License
Classifier: Operating System :: OS Independent
Classifier: Programming Language :: Python
Classifier: Topic :: Internet :: WWW/HTTP :: Dynamic Content
Classifier: Topic :: Software Development :: Libraries :: Python Modules
